data_gouv_mcp_server/__init__.py
data_gouv_mcp_server/main.py
data_gouv_mcp_server/infra/clients/http_client.py
data_gouv_mcp_server/test/test_search_dataset.py
data_gouv_fr_mcp_server-0.1.3.dist-info/METADATA
data_gouv_fr_mcp_server-0.1.3.dist-info/WHEEL
data_gouv_fr_mcp_server-0.1.3.dist-info/entry_points.txt
data_gouv_fr_mcp_server-0.1.3.dist-info/top_level.txt
data_gouv_fr_mcp_server-0.1.3.dist-info/RECORD
